pyrus_nn/_version.py
pyrus_nn/layers.py
pyrus_nn/models.py
pyrus_nn/__init__.py
pyrus_nn/rust/pyrus_nn.so
pyrus_nn/rust/__init__.py
tests/test_pyrus_sequential.py
tests/__init__.py
pyrust_nn-0.1.1.dist-info/WHEEL
pyrust_nn-0.1.1.dist-info/RECORD
pyrust_nn-0.1.1.dist-info/top_level.txt
pyrust_nn-0.1.1.dist-info/METADATA
