Metadata-Version: 2.1
Name: pyrust-nn
Version: 0.1.1
Summary: Micro Neural Network framework implemented in Rust w/ Python bindings
Home-page: UNKNOWN
Author: Miles Granger
Author-email: miles59923@gmail.com
License: UNKNOWN
Platform: UNKNOWN
Classifier: Intended Audience :: Developers
Classifier: Natural Language :: English
Classifier: Programming Language :: Python :: 3.6
Classifier: Programming Language :: Python :: 3.7
